environmental_biophysics-0.0.6.dist-info/METADATA
environmental_biophysics-0.0.6.dist-info/WHEEL
environmental_biophysics/__init__.py
environmental_biophysics/crop_model/__init__.py
environmental_biophysics/crop_model/crop_class.py
environmental_biophysics/crop_model/soil_class.py
environmental_biophysics/environmental_constants.py
environmental_biophysics/gas.py
environmental_biophysics/soil.py
environmental_biophysics/solar_radiation.py
environmental_biophysics-0.0.6.dist-info/RECORD
