Metadata-Version: 2.1
Name: environmental-biophysics
Version: 0.0.6
Summary: Add your description here
Author: Gustavo Camargo
Requires-Python: ~=3.12
Requires-Dist: numpy~=2.0.1
Requires-Dist: pyright~=1.1.374
Requires-Dist: pytest-cov~=5.0.0
Requires-Dist: mkdocs-material~=9.5.30
Requires-Dist: mkdocstrings~=0.25.2
Requires-Dist: pytest~=8.3.2
Requires-Dist: mkdocstrings-python~=1.10.7
Requires-Dist: mkdocs-macros-plugin~=1.0.5
Requires-Dist: pandas~=2.2.2
Requires-Dist: xlwt~=1.3.0
